{
  "metadata": {
    "title": "Generated Torah Word Occurrences",
    "version": "0.1",
    "artifact_type": "word_occurrences",
    "corpus_id": "parsed_bereishis_3_17_to_3_24_staged",
    "status": "staged",
    "pesukim_count": 8,
    "sefer": "Bereishis",
    "range": {
      "start": {
        "sefer": "Bereishis",
        "perek": 3,
        "pasuk": 17
      },
      "end": {
        "sefer": "Bereishis",
        "perek": 3,
        "pasuk": 24
      }
    },
    "source_files": [
      "data/source/bereishis_3_17_to_3_24.json"
    ],
    "declared_source_range": "3:17-3:24"
  },
  "occurrences": [
    {
      "pasuk_id": "bereishis_3_17",
      "token_index": 0,
      "surface": "וּלְאָדָם",
      "normalized": "ולאדם",
      "analysis_index": 0
    },
    {
      "pasuk_id": "bereishis_3_17",
      "token_index": 1,
      "surface": "אָמַר",
      "normalized": "אמר",
      "analysis_index": 0
    },
    {
      "pasuk_id": "bereishis_3_17",
      "token_index": 2,
      "surface": "כִּי",
      "normalized": "כי",
      "analysis_index": 0
    },
    {
      "pasuk_id": "bereishis_3_17",
      "token_index": 3,
      "surface": "שָׁמַעְתָּ",
      "normalized": "שמעת",
      "analysis_index": 0
    },
    {
      "pasuk_id": "bereishis_3_17",
      "token_index": 4,
      "surface": "לְקוֹל",
      "normalized": "לקול",
      "analysis_index": 0
    },
    {
      "pasuk_id": "bereishis_3_17",
      "token_index": 5,
      "surface": "אִשְׁתֶּךָ",
      "normalized": "אשתך",
      "analysis_index": 0
    },
    {
      "pasuk_id": "bereishis_3_17",
      "token_index": 6,
      "surface": "וַתֹּאכַל",
      "normalized": "ותאכל",
      "analysis_index": 0
    },
    {
      "pasuk_id": "bereishis_3_17",
      "token_index": 7,
      "surface": "מִן",
      "normalized": "מן",
      "analysis_index": 0
    },
    {
      "pasuk_id": "bereishis_3_17",
      "token_index": 8,
      "surface": "הָעֵץ",
      "normalized": "העץ",
      "analysis_index": 0
    },
    {
      "pasuk_id": "bereishis_3_17",
      "token_index": 9,
      "surface": "אֲשֶׁר",
      "normalized": "אשר",
      "analysis_index": 0
    },
    {
      "pasuk_id": "bereishis_3_17",
      "token_index": 10,
      "surface": "צִוִּיתִיךָ",
      "normalized": "צויתיך",
      "analysis_index": 0
    },
    {
      "pasuk_id": "bereishis_3_17",
      "token_index": 11,
      "surface": "לֵאמֹר",
      "normalized": "לאמר",
      "analysis_index": 0
    },
    {
      "pasuk_id": "bereishis_3_17",
      "token_index": 12,
      "surface": "לֹא",
      "normalized": "לא",
      "analysis_index": 0
    },
    {
      "pasuk_id": "bereishis_3_17",
      "token_index": 13,
      "surface": "תֹאכַל",
      "normalized": "תאכל",
      "analysis_index": 0
    },
    {
      "pasuk_id": "bereishis_3_17",
      "token_index": 14,
      "surface": "מִמֶּנּוּ",
      "normalized": "ממנו",
      "analysis_index": 0
    },
    {
      "pasuk_id": "bereishis_3_17",
      "token_index": 15,
      "surface": "אֲרוּרָה",
      "normalized": "ארורה",
      "analysis_index": 0
    },
    {
      "pasuk_id": "bereishis_3_17",
      "token_index": 16,
      "surface": "הָאֲדָמָה",
      "normalized": "האדמה",
      "analysis_index": 0
    },
    {
      "pasuk_id": "bereishis_3_17",
      "token_index": 17,
      "surface": "בַּעֲבוּרֶךָ",
      "normalized": "בעבורך",
      "analysis_index": 0
    },
    {
      "pasuk_id": "bereishis_3_17",
      "token_index": 18,
      "surface": "בְּעִצָּבוֹן",
      "normalized": "בעצבון",
      "analysis_index": 0
    },
    {
      "pasuk_id": "bereishis_3_17",
      "token_index": 19,
      "surface": "תֹּאכֲלֶנָּה",
      "normalized": "תאכלנה",
      "analysis_index": 0
    },
    {
      "pasuk_id": "bereishis_3_17",
      "token_index": 20,
      "surface": "כֹּל",
      "normalized": "כל",
      "analysis_index": 0
    },
    {
      "pasuk_id": "bereishis_3_17",
      "token_index": 21,
      "surface": "יְמֵי",
      "normalized": "ימי",
      "analysis_index": 0
    },
    {
      "pasuk_id": "bereishis_3_17",
      "token_index": 22,
      "surface": "חַיֶּיךָ",
      "normalized": "חייך",
      "analysis_index": 0
    },
    {
      "pasuk_id": "bereishis_3_18",
      "token_index": 0,
      "surface": "וְקוֹץ",
      "normalized": "וקוץ",
      "analysis_index": 0
    },
    {
      "pasuk_id": "bereishis_3_18",
      "token_index": 1,
      "surface": "וְדַרְדַּר",
      "normalized": "ודרדר",
      "analysis_index": 0
    },
    {
      "pasuk_id": "bereishis_3_18",
      "token_index": 2,
      "surface": "תַּצְמִיחַ",
      "normalized": "תצמיח",
      "analysis_index": 0
    },
    {
      "pasuk_id": "bereishis_3_18",
      "token_index": 3,
      "surface": "לָךְ",
      "normalized": "לך",
      "analysis_index": 0
    },
    {
      "pasuk_id": "bereishis_3_18",
      "token_index": 4,
      "surface": "וְאָכַלְתָּ",
      "normalized": "ואכלת",
      "analysis_index": 0
    },
    {
      "pasuk_id": "bereishis_3_18",
      "token_index": 5,
      "surface": "אֶת",
      "normalized": "את",
      "analysis_index": 0
    },
    {
      "pasuk_id": "bereishis_3_18",
      "token_index": 6,
      "surface": "עֵשֶׂב",
      "normalized": "עשב",
      "analysis_index": 0
    },
    {
      "pasuk_id": "bereishis_3_18",
      "token_index": 7,
      "surface": "הַשָּׂדֶה",
      "normalized": "השדה",
      "analysis_index": 0
    },
    {
      "pasuk_id": "bereishis_3_19",
      "token_index": 0,
      "surface": "בְּזֵעַת",
      "normalized": "בזעת",
      "analysis_index": 0
    },
    {
      "pasuk_id": "bereishis_3_19",
      "token_index": 1,
      "surface": "אַפֶּיךָ",
      "normalized": "אפיך",
      "analysis_index": 0
    },
    {
      "pasuk_id": "bereishis_3_19",
      "token_index": 2,
      "surface": "תֹּאכַל",
      "normalized": "תאכל",
      "analysis_index": 0
    },
    {
      "pasuk_id": "bereishis_3_19",
      "token_index": 3,
      "surface": "לֶחֶם",
      "normalized": "לחם",
      "analysis_index": 0
    },
    {
      "pasuk_id": "bereishis_3_19",
      "token_index": 4,
      "surface": "עַד",
      "normalized": "עד",
      "analysis_index": 0
    },
    {
      "pasuk_id": "bereishis_3_19",
      "token_index": 5,
      "surface": "שׁוּבְךָ",
      "normalized": "שובך",
      "analysis_index": 0
    },
    {
      "pasuk_id": "bereishis_3_19",
      "token_index": 6,
      "surface": "אֶל",
      "normalized": "אל",
      "analysis_index": 0
    },
    {
      "pasuk_id": "bereishis_3_19",
      "token_index": 7,
      "surface": "הָאֲדָמָה",
      "normalized": "האדמה",
      "analysis_index": 0
    },
    {
      "pasuk_id": "bereishis_3_19",
      "token_index": 8,
      "surface": "כִּי",
      "normalized": "כי",
      "analysis_index": 0
    },
    {
      "pasuk_id": "bereishis_3_19",
      "token_index": 9,
      "surface": "מִמֶּנָּה",
      "normalized": "ממנה",
      "analysis_index": 0
    },
    {
      "pasuk_id": "bereishis_3_19",
      "token_index": 10,
      "surface": "לֻקָּחְתָּ",
      "normalized": "לקחת",
      "analysis_index": 0
    },
    {
      "pasuk_id": "bereishis_3_19",
      "token_index": 11,
      "surface": "כִּי",
      "normalized": "כי",
      "analysis_index": 0
    },
    {
      "pasuk_id": "bereishis_3_19",
      "token_index": 12,
      "surface": "עָפָר",
      "normalized": "עפר",
      "analysis_index": 0
    },
    {
      "pasuk_id": "bereishis_3_19",
      "token_index": 13,
      "surface": "אַתָּה",
      "normalized": "אתה",
      "analysis_index": 0
    },
    {
      "pasuk_id": "bereishis_3_19",
      "token_index": 14,
      "surface": "וְאֶל",
      "normalized": "ואל",
      "analysis_index": 0
    },
    {
      "pasuk_id": "bereishis_3_19",
      "token_index": 15,
      "surface": "עָפָר",
      "normalized": "עפר",
      "analysis_index": 0
    },
    {
      "pasuk_id": "bereishis_3_19",
      "token_index": 16,
      "surface": "תָּשׁוּב",
      "normalized": "תשוב",
      "analysis_index": 0
    },
    {
      "pasuk_id": "bereishis_3_20",
      "token_index": 0,
      "surface": "וַיִּקְרָא",
      "normalized": "ויקרא",
      "analysis_index": 0
    },
    {
      "pasuk_id": "bereishis_3_20",
      "token_index": 1,
      "surface": "הָאָדָם",
      "normalized": "האדם",
      "analysis_index": 0
    },
    {
      "pasuk_id": "bereishis_3_20",
      "token_index": 2,
      "surface": "שֵׁם",
      "normalized": "שם",
      "analysis_index": 0
    },
    {
      "pasuk_id": "bereishis_3_20",
      "token_index": 3,
      "surface": "אִשְׁתּוֹ",
      "normalized": "אשתו",
      "analysis_index": 0
    },
    {
      "pasuk_id": "bereishis_3_20",
      "token_index": 4,
      "surface": "חַוָּה",
      "normalized": "חוה",
      "analysis_index": 0
    },
    {
      "pasuk_id": "bereishis_3_20",
      "token_index": 5,
      "surface": "כִּי",
      "normalized": "כי",
      "analysis_index": 0
    },
    {
      "pasuk_id": "bereishis_3_20",
      "token_index": 6,
      "surface": "הִוא",
      "normalized": "הוא",
      "analysis_index": 0
    },
    {
      "pasuk_id": "bereishis_3_20",
      "token_index": 7,
      "surface": "הָיְתָה",
      "normalized": "היתה",
      "analysis_index": 0
    },
    {
      "pasuk_id": "bereishis_3_20",
      "token_index": 8,
      "surface": "אֵם",
      "normalized": "אם",
      "analysis_index": 0
    },
    {
      "pasuk_id": "bereishis_3_20",
      "token_index": 9,
      "surface": "כָּל",
      "normalized": "כל",
      "analysis_index": 0
    },
    {
      "pasuk_id": "bereishis_3_20",
      "token_index": 10,
      "surface": "חָי",
      "normalized": "חי",
      "analysis_index": 0
    },
    {
      "pasuk_id": "bereishis_3_21",
      "token_index": 0,
      "surface": "וַיַּעַשׂ",
      "normalized": "ויעש",
      "analysis_index": 0
    },
    {
      "pasuk_id": "bereishis_3_21",
      "token_index": 1,
      "surface": "יְהוָה",
      "normalized": "יהוה",
      "analysis_index": 0
    },
    {
      "pasuk_id": "bereishis_3_21",
      "token_index": 2,
      "surface": "אֱלֹהִים",
      "normalized": "אלהים",
      "analysis_index": 0
    },
    {
      "pasuk_id": "bereishis_3_21",
      "token_index": 3,
      "surface": "לְאָדָם",
      "normalized": "לאדם",
      "analysis_index": 0
    },
    {
      "pasuk_id": "bereishis_3_21",
      "token_index": 4,
      "surface": "וּלְאִשְׁתּוֹ",
      "normalized": "ולאשתו",
      "analysis_index": 0
    },
    {
      "pasuk_id": "bereishis_3_21",
      "token_index": 5,
      "surface": "כָּתְנוֹת",
      "normalized": "כתנות",
      "analysis_index": 0
    },
    {
      "pasuk_id": "bereishis_3_21",
      "token_index": 6,
      "surface": "עוֹר",
      "normalized": "עור",
      "analysis_index": 0
    },
    {
      "pasuk_id": "bereishis_3_21",
      "token_index": 7,
      "surface": "וַיַּלְבִּשֵׁם",
      "normalized": "וילבשם",
      "analysis_index": 0
    },
    {
      "pasuk_id": "bereishis_3_22",
      "token_index": 0,
      "surface": "וַיֹּאמֶר",
      "normalized": "ויאמר",
      "analysis_index": 0
    },
    {
      "pasuk_id": "bereishis_3_22",
      "token_index": 1,
      "surface": "יְהוָה",
      "normalized": "יהוה",
      "analysis_index": 0
    },
    {
      "pasuk_id": "bereishis_3_22",
      "token_index": 2,
      "surface": "אֱלֹהִים",
      "normalized": "אלהים",
      "analysis_index": 0
    },
    {
      "pasuk_id": "bereishis_3_22",
      "token_index": 3,
      "surface": "הֵן",
      "normalized": "הן",
      "analysis_index": 0
    },
    {
      "pasuk_id": "bereishis_3_22",
      "token_index": 4,
      "surface": "הָאָדָם",
      "normalized": "האדם",
      "analysis_index": 0
    },
    {
      "pasuk_id": "bereishis_3_22",
      "token_index": 5,
      "surface": "הָיָה",
      "normalized": "היה",
      "analysis_index": 0
    },
    {
      "pasuk_id": "bereishis_3_22",
      "token_index": 6,
      "surface": "כְּאַחַד",
      "normalized": "כאחד",
      "analysis_index": 0
    },
    {
      "pasuk_id": "bereishis_3_22",
      "token_index": 7,
      "surface": "מִמֶּנּוּ",
      "normalized": "ממנו",
      "analysis_index": 0
    },
    {
      "pasuk_id": "bereishis_3_22",
      "token_index": 8,
      "surface": "לָדַעַת",
      "normalized": "לדעת",
      "analysis_index": 0
    },
    {
      "pasuk_id": "bereishis_3_22",
      "token_index": 9,
      "surface": "טוֹב",
      "normalized": "טוב",
      "analysis_index": 0
    },
    {
      "pasuk_id": "bereishis_3_22",
      "token_index": 10,
      "surface": "וָרָע",
      "normalized": "ורע",
      "analysis_index": 0
    },
    {
      "pasuk_id": "bereishis_3_22",
      "token_index": 11,
      "surface": "וְעַתָּה",
      "normalized": "ועתה",
      "analysis_index": 0
    },
    {
      "pasuk_id": "bereishis_3_22",
      "token_index": 12,
      "surface": "פֶּן",
      "normalized": "פן",
      "analysis_index": 0
    },
    {
      "pasuk_id": "bereishis_3_22",
      "token_index": 13,
      "surface": "יִשְׁלַח",
      "normalized": "ישלח",
      "analysis_index": 0
    },
    {
      "pasuk_id": "bereishis_3_22",
      "token_index": 14,
      "surface": "יָדוֹ",
      "normalized": "ידו",
      "analysis_index": 0
    },
    {
      "pasuk_id": "bereishis_3_22",
      "token_index": 15,
      "surface": "וְלָקַח",
      "normalized": "ולקח",
      "analysis_index": 0
    },
    {
      "pasuk_id": "bereishis_3_22",
      "token_index": 16,
      "surface": "גַּם",
      "normalized": "גם",
      "analysis_index": 0
    },
    {
      "pasuk_id": "bereishis_3_22",
      "token_index": 17,
      "surface": "מֵעֵץ",
      "normalized": "מעץ",
      "analysis_index": 0
    },
    {
      "pasuk_id": "bereishis_3_22",
      "token_index": 18,
      "surface": "הַחַיִּים",
      "normalized": "החיים",
      "analysis_index": 0
    },
    {
      "pasuk_id": "bereishis_3_22",
      "token_index": 19,
      "surface": "וְאָכַל",
      "normalized": "ואכל",
      "analysis_index": 0
    },
    {
      "pasuk_id": "bereishis_3_22",
      "token_index": 20,
      "surface": "וָחַי",
      "normalized": "וחי",
      "analysis_index": 0
    },
    {
      "pasuk_id": "bereishis_3_22",
      "token_index": 21,
      "surface": "לְעֹלָם",
      "normalized": "לעלם",
      "analysis_index": 0
    },
    {
      "pasuk_id": "bereishis_3_23",
      "token_index": 0,
      "surface": "וַיְשַׁלְּחֵהוּ",
      "normalized": "וישלחהו",
      "analysis_index": 0
    },
    {
      "pasuk_id": "bereishis_3_23",
      "token_index": 1,
      "surface": "יְהוָה",
      "normalized": "יהוה",
      "analysis_index": 0
    },
    {
      "pasuk_id": "bereishis_3_23",
      "token_index": 2,
      "surface": "אֱלֹהִים",
      "normalized": "אלהים",
      "analysis_index": 0
    },
    {
      "pasuk_id": "bereishis_3_23",
      "token_index": 3,
      "surface": "מִגַּן",
      "normalized": "מגן",
      "analysis_index": 0
    },
    {
      "pasuk_id": "bereishis_3_23",
      "token_index": 4,
      "surface": "עֵדֶן",
      "normalized": "עדן",
      "analysis_index": 0
    },
    {
      "pasuk_id": "bereishis_3_23",
      "token_index": 5,
      "surface": "לַעֲבֹד",
      "normalized": "לעבד",
      "analysis_index": 0
    },
    {
      "pasuk_id": "bereishis_3_23",
      "token_index": 6,
      "surface": "אֶת",
      "normalized": "את",
      "analysis_index": 0
    },
    {
      "pasuk_id": "bereishis_3_23",
      "token_index": 7,
      "surface": "הָאֲדָמָה",
      "normalized": "האדמה",
      "analysis_index": 0
    },
    {
      "pasuk_id": "bereishis_3_23",
      "token_index": 8,
      "surface": "אֲשֶׁר",
      "normalized": "אשר",
      "analysis_index": 0
    },
    {
      "pasuk_id": "bereishis_3_23",
      "token_index": 9,
      "surface": "לֻקַּח",
      "normalized": "לקח",
      "analysis_index": 0
    },
    {
      "pasuk_id": "bereishis_3_23",
      "token_index": 10,
      "surface": "מִשָּׁם",
      "normalized": "משם",
      "analysis_index": 0
    },
    {
      "pasuk_id": "bereishis_3_24",
      "token_index": 0,
      "surface": "וַיְגָרֶשׁ",
      "normalized": "ויגרש",
      "analysis_index": 0
    },
    {
      "pasuk_id": "bereishis_3_24",
      "token_index": 1,
      "surface": "אֶת",
      "normalized": "את",
      "analysis_index": 0
    },
    {
      "pasuk_id": "bereishis_3_24",
      "token_index": 2,
      "surface": "הָאָדָם",
      "normalized": "האדם",
      "analysis_index": 0
    },
    {
      "pasuk_id": "bereishis_3_24",
      "token_index": 3,
      "surface": "וַיַּשְׁכֵּן",
      "normalized": "וישכן",
      "analysis_index": 0
    },
    {
      "pasuk_id": "bereishis_3_24",
      "token_index": 4,
      "surface": "מִקֶּדֶם",
      "normalized": "מקדם",
      "analysis_index": 0
    },
    {
      "pasuk_id": "bereishis_3_24",
      "token_index": 5,
      "surface": "לְגַן",
      "normalized": "לגן",
      "analysis_index": 0
    },
    {
      "pasuk_id": "bereishis_3_24",
      "token_index": 6,
      "surface": "עֵדֶן",
      "normalized": "עדן",
      "analysis_index": 0
    },
    {
      "pasuk_id": "bereishis_3_24",
      "token_index": 7,
      "surface": "אֶת",
      "normalized": "את",
      "analysis_index": 0
    },
    {
      "pasuk_id": "bereishis_3_24",
      "token_index": 8,
      "surface": "הַכְּרֻבִים",
      "normalized": "הכרבים",
      "analysis_index": 0
    },
    {
      "pasuk_id": "bereishis_3_24",
      "token_index": 9,
      "surface": "וְאֵת",
      "normalized": "ואת",
      "analysis_index": 0
    },
    {
      "pasuk_id": "bereishis_3_24",
      "token_index": 10,
      "surface": "לַהַט",
      "normalized": "להט",
      "analysis_index": 0
    },
    {
      "pasuk_id": "bereishis_3_24",
      "token_index": 11,
      "surface": "הַחֶרֶב",
      "normalized": "החרב",
      "analysis_index": 0
    },
    {
      "pasuk_id": "bereishis_3_24",
      "token_index": 12,
      "surface": "הַמִּתְהַפֶּכֶת",
      "normalized": "המתהפכת",
      "analysis_index": 0
    },
    {
      "pasuk_id": "bereishis_3_24",
      "token_index": 13,
      "surface": "לִשְׁמֹר",
      "normalized": "לשמר",
      "analysis_index": 0
    },
    {
      "pasuk_id": "bereishis_3_24",
      "token_index": 14,
      "surface": "אֶת",
      "normalized": "את",
      "analysis_index": 0
    },
    {
      "pasuk_id": "bereishis_3_24",
      "token_index": 15,
      "surface": "דֶּרֶךְ",
      "normalized": "דרך",
      "analysis_index": 0
    },
    {
      "pasuk_id": "bereishis_3_24",
      "token_index": 16,
      "surface": "עֵץ",
      "normalized": "עץ",
      "analysis_index": 0
    },
    {
      "pasuk_id": "bereishis_3_24",
      "token_index": 17,
      "surface": "הַחַיִּים",
      "normalized": "החיים",
      "analysis_index": 0
    }
  ]
}
