{
  "metadata": {
    "title": "Bereishis source text",
    "range": "3:17-3:24",
    "format": "sefer,perek,pasuk,text"
  },
  "pesukim": [
    {
      "sefer": "Bereishis",
      "perek": 3,
      "pasuk": 17,
      "text": "וּלְאָדָם אָמַר, כִּי־שָׁמַעְתָּ לְקוֹל אִשְׁתֶּךָ, וַתֹּאכַל, מִן־הָעֵץ, אֲשֶׁר צִוִּיתִיךָ לֵאמֹר, לֹא תֹאכַל מִמֶּנּוּ; אֲרוּרָה הָאֲדָמָה, בַּעֲבוּרֶךָ, בְּעִצָּבוֹן, תֹּאכֲלֶנָּה, כֹּל יְמֵי חַיֶּיךָ."
    },
    {
      "sefer": "Bereishis",
      "perek": 3,
      "pasuk": 18,
      "text": "וְקוֹץ וְדַרְדַּר, תַּצְמִיחַ לָךְ; וְאָכַלְתָּ, אֶת־עֵשֶׂב הַשָּׂדֶה."
    },
    {
      "sefer": "Bereishis",
      "perek": 3,
      "pasuk": 19,
      "text": "בְּזֵעַת אַפֶּיךָ, תֹּאכַל לֶחֶם, עַד שׁוּבְךָ, אֶל־הָאֲדָמָה: כִּי מִמֶּנָּה לֻקָּחְתָּ, כִּי־עָפָר אַתָּה, וְאֶל־עָפָר תָּשׁוּב."
    },
    {
      "sefer": "Bereishis",
      "perek": 3,
      "pasuk": 20,
      "text": "וַיִּקְרָא הָאָדָם, שֵׁם אִשְׁתּוֹ חַוָּה: כִּי הִוא הָיְתָה, אֵם כָּל־חָי."
    },
    {
      "sefer": "Bereishis",
      "perek": 3,
      "pasuk": 21,
      "text": "וַיַּעַשׂ יְהוָה אֱלֹהִים, לְאָדָם וּלְאִשְׁתּוֹ, כָּתְנוֹת עוֹר; וַיַּלְבִּשֵׁם."
    },
    {
      "sefer": "Bereishis",
      "perek": 3,
      "pasuk": 22,
      "text": "וַיֹּאמֶר יְהוָה אֱלֹהִים, הֵן הָאָדָם, הָיָה כְּאַחַד מִמֶּנּוּ, לָדַעַת, טוֹב וָרָע; וְעַתָּה, פֶּן־יִשְׁלַח יָדוֹ, וְלָקַח גַּם מֵעֵץ הַחַיִּים, וְאָכַל, וָחַי לְעֹלָם."
    },
    {
      "sefer": "Bereishis",
      "perek": 3,
      "pasuk": 23,
      "text": "וַיְשַׁלְּחֵהוּ יְהוָה אֱלֹהִים, מִגַּן־עֵדֶן, לַעֲבֹד אֶת־הָאֲדָמָה, אֲשֶׁר לֻקַּח מִשָּׁם."
    },
    {
      "sefer": "Bereishis",
      "perek": 3,
      "pasuk": 24,
      "text": "וַיְגָרֶשׁ, אֶת־הָאָדָם; וַיַּשְׁכֵּן מִקֶּדֶם לְגַן־עֵדֶן, אֶת־הַכְּרֻבִים, וְאֵת לַהַט הַחֶרֶב, הַמִּתְהַפֶּכֶת, לִשְׁמֹר, אֶת־דֶּרֶךְ עֵץ הַחַיִּים."
    }
  ]
}
